MANIFEST.in
README.md
setup.py
noolite_mqtt_webserver/__init__.py
noolite_mqtt_webserver/accessory_import.py
noolite_mqtt_webserver/main.py
noolite_mqtt_webserver/server.py
noolite_mqtt_webserver/tester.py
noolite_mqtt_webserver/tester_mqtt.py
noolite_mqtt_webserver/utils.py
noolite_mqtt_webserver.egg-info/PKG-INFO
noolite_mqtt_webserver.egg-info/SOURCES.txt
noolite_mqtt_webserver.egg-info/dependency_links.txt
noolite_mqtt_webserver.egg-info/entry_points.txt
noolite_mqtt_webserver.egg-info/requires.txt
noolite_mqtt_webserver.egg-info/top_level.txt
noolite_mqtt_webserver/noolite_mqtt/__init__.py
noolite_mqtt_webserver/noolite_mqtt/accessories.py
noolite_mqtt_webserver/noolite_mqtt/main.py
noolite_mqtt_webserver/noolite_mqtt/noolite_commands.py
noolite_mqtt_webserver/noolite_mqtt/utils.py
noolite_mqtt_webserver/static/.DS_Store
noolite_mqtt_webserver/static/bootstrap-3.3.7/.DS_Store
noolite_mqtt_webserver/static/bootstrap-3.3.7/css/bootstrap-theme.css
noolite_mqtt_webserver/static/bootstrap-3.3.7/css/bootstrap-theme.css.map
noolite_mqtt_webserver/static/bootstrap-3.3.7/css/bootstrap-theme.min.css
noolite_mqtt_webserver/static/bootstrap-3.3.7/css/bootstrap-theme.min.css.map
noolite_mqtt_webserver/static/bootstrap-3.3.7/css/bootstrap.css
noolite_mqtt_webserver/static/bootstrap-3.3.7/css/bootstrap.css.map
noolite_mqtt_webserver/static/bootstrap-3.3.7/css/bootstrap.min.css
noolite_mqtt_webserver/static/bootstrap-3.3.7/css/bootstrap.min.css.map
noolite_mqtt_webserver/static/bootstrap-3.3.7/fonts/glyphicons-halflings-regular.eot
noolite_mqtt_webserver/static/bootstrap-3.3.7/fonts/glyphicons-halflings-regular.svg
noolite_mqtt_webserver/static/bootstrap-3.3.7/fonts/glyphicons-halflings-regular.ttf
noolite_mqtt_webserver/static/bootstrap-3.3.7/fonts/glyphicons-halflings-regular.woff
noolite_mqtt_webserver/static/bootstrap-3.3.7/fonts/glyphicons-halflings-regular.woff2
noolite_mqtt_webserver/static/bootstrap-3.3.7/js/bootstrap.js
noolite_mqtt_webserver/static/bootstrap-3.3.7/js/bootstrap.min.js
noolite_mqtt_webserver/static/bootstrap-3.3.7/js/npm.js
noolite_mqtt_webserver/static/css/base.css
noolite_mqtt_webserver/static/js/accessories.js
noolite_mqtt_webserver/static/js/api.js
noolite_mqtt_webserver/static/js/jquery-3.1.1.min.js
