Metadata-Version: 1.0
Name: noolite-mqtt-webserver
Version: 0.1.2
Summary: Web server for NooLite.
Home-page: https://bitbucket.org/AlekseevAV/noolite-mqtt-web-server
Author: UNKNOWN
Author-email: UNKNOWN
License: UNKNOWN
Platform: UNKNOWN
